Metadata-Version: 1.1
Name: libpy
Version: 0.2.3
Summary: Utilities for writing C++ extension modules.
Home-page: https://github.com/quantopian/libpy
Author: Quantopian Inc.
Author-email: opensource@quantopian.com
License: Apache 2.0
Platform: UNKNOWN
Classifier: Development Status :: 4 - Beta
Classifier: License :: OSI Approved :: Apache Software License
Classifier: Natural Language :: English
Classifier: Topic :: Software Development
Classifier: Programming Language :: Python
Classifier: Programming Language :: Python :: 3.5
Classifier: Programming Language :: Python :: 3.6
Classifier: Programming Language :: Python :: 3.7
Classifier: Programming Language :: Python :: 3.8
Classifier: Programming Language :: Python :: Implementation :: CPython
Classifier: Programming Language :: C++
Classifier: Operating System :: POSIX
Classifier: Intended Audience :: Developers
